{"pageContext":{"branches":[{"node":{"id":"dc6e0d96-3388-5960-b36c-ce0744479bd6","status":"N","intake":60,"code":"CS","gender":1,"name":"Computer Science and Engg.","ccode":4677,"yos":2013}},{"node":{"id":"47141391-0bcb-590d-9740-cd3c0d4bdb0e","status":"N","intake":60,"code":"CE","gender":1,"name":"Civil Engineering","ccode":4677,"yos":2013}},{"node":{"id":"752fc2a1-52df-58f6-9c49-51d88cf62e03","status":"N","intake":60,"code":"EE","gender":1,"name":"Electrical and Elec. Engg.","ccode":4677,"yos":2013}},{"node":{"id":"1e80b97c-26bd-5fb3-a075-2e6d6355e8ec","status":"N","intake":60,"code":"EC","gender":1,"name":"Electronics and Comm Engg.","ccode":4677,"yos":2013}},{"node":{"id":"c5a0ac15-14e1-54bc-a195-60e7f50c5233","status":"N","intake":60,"code":"ME","gender":1,"name":"Mechanical Engineering","ccode":4677,"yos":2013}}],"collegeData":{"id":"e362686d-6dc3-50e0-ae85-a7fc92d84f62","catcode":4,"gender":1,"collcode":4677,"lat":8.2666,"lng":77.2379,"place":"ChIJuRX5hJv_BDsRgUsGO0_sVnQ","name":"Lourdes Mount College of Engineering & Technology","add1":"Marthandam – Karungal Road, Chunda vilai, Mullangana Vilai, Kanyakumari","add2":"Marthandam – Karungal Road, Chunda vilai, Mullangana Vilai, Kanyakumari, Tamil Nadu 629195, India","locality":"Kanyakumari","slug":"lourdes-mount-college-of-engineering-technology-kanyakumari-4677","phone_no1":"04651 267 733","www":"http://www.lourdesmountcollege.com","autonomous":"No","mess_bill_g":"2500","caution_deposit_b":5000,"room_rent_boys":"800","transport_option":"Optional","electricity_charges_g":"200","caution_deposit_g":5000,"admission_fee_b":500,"accno1":2147483647,"phone_1":"04651-267735","yos":2013,"mess_type_b":"Veg/Non-Veg","mess_bill_b_myr":1,"room_rent_g_myr":1,"mess_bill_b":"2500","room_rent_g":"800","elec_charges_g_myr":1,"room_rent_b_myr":1,"transport":"Yes","elec_charges_b_myr":1,"a_boys":"Yes","est_charges_b":"0","per_rental_g":"Permanent","per_rental_b":"Permanent","a_girls":"Yes","electricity_charges_b":"200","fax":"04651-267733  ","mess_type_g":"Veg/Non-Veg","phone_2":"04651-266744","admission_fee_g":500,"url":"www.lourdesmountcollege.com","est_charges_g":"0","mobile":"9488160281","mess_bill_g_myr":1,"minority":"No"}}}