{"pageContext":{"branches":[{"node":{"id":"5238cd92-1604-5e4b-bef3-17a710a28566","status":"N","intake":120,"code":"CS","gender":1,"name":"Computer Science and Engg.","ccode":1452,"yos":2010}},{"node":{"id":"f028084f-b14d-5b83-9ff4-670fc37d9e3f","status":"N","intake":120,"code":"CE","gender":1,"name":"Civil Engineering","ccode":1452,"yos":2010}},{"node":{"id":"0369fbe5-3c9b-5a04-bc5b-1d06268718f1","status":"N","intake":120,"code":"EC","gender":1,"name":"Electronics and Comm Engg.","ccode":1452,"yos":2011}},{"node":{"id":"b875118a-c3d2-5f6c-a308-169c8bea72fe","status":"N","intake":60,"code":"EE","gender":1,"name":"Electrical and Elec. Engg.","ccode":1452,"yos":2010}},{"node":{"id":"60e1d338-556d-55d1-ba5b-a07a62626db9","status":"N","intake":240,"code":"ME","gender":1,"name":"Mechanical Engineering","ccode":1452,"yos":2010}}],"collegeData":{"id":"fdfb62e4-9d4c-569d-8f63-811c8a0b2c1b","catcode":4,"gender":1,"collcode":1452,"lat":12.886,"lng":80.0608,"place":"ChIJvSrccXn2UjoRsGfQqcaj7ss","name":"PERI Institute of Technology","add1":"No.1, Near West Tambaram, Mannivakkam, Chennai","add2":"No.1, Near West Tambaram, Mannivakkam, Chennai, Tamil Nadu 600048, India","locality":"Chennai","slug":"peri-institute-of-technology-chennai-kanchipuram-1452","phone_no1":"096771 30347","www":"http://www.periit.com/","autonomous":"No","mess_bill_g":"3500","caution_deposit_b":0,"room_rent_boys":"1000","transport_option":"Optional","electricity_charges_g":"420","caution_deposit_g":0,"admission_fee_b":1000,"accno1":2147483647,"phone_1":"044-66813333","yos":2010,"mess_type_b":"Veg/Non-Veg","mess_bill_b_myr":1,"room_rent_g_myr":1,"mess_bill_b":"3500","room_rent_g":"1000","elec_charges_g_myr":1,"room_rent_b_myr":1,"transport":"Yes","elec_charges_b_myr":1,"a_boys":"Yes","est_charges_b":"5000","per_rental_g":"Permanent","per_rental_b":"Permanent","a_girls":"Yes","electricity_charges_b":"420","fax":"044-66813300","mess_type_g":"Veg/Non-Veg","phone_2":"9677130344","admission_fee_g":1000,"url":"www.periit.com","est_charges_g":"5000","mobile":"9677130343","mess_bill_g_myr":1,"minority":"No"}}}