{"pageContext":{"branches":[{"node":{"id":"a4a5623e-d6ea-5b61-a03b-709cc872a138","status":"Y","intake":180,"code":"CS","gender":1,"name":"Computer Science and Engg.","ccode":2601,"yos":1987}},{"node":{"id":"af4d0eb5-e179-5627-9ce7-ecbc1bdff065","status":"Y","intake":240,"code":"EC","gender":1,"name":"Electronics and Comm Engg.","ccode":2601,"yos":1987}},{"node":{"id":"30831540-ec65-5f63-86a7-483adb4da31e","status":"Y","intake":120,"code":"EE","gender":1,"name":"Electrical and Elec. Engg.","ccode":2601,"yos":1992}},{"node":{"id":"264ba1c8-e7ff-5201-8ca2-f5b2cd938c10","status":"Y","intake":60,"code":"EI","gender":1,"name":"Electronics and Instru Engg.","ccode":2601,"yos":2007}},{"node":{"id":"170115d5-1682-5325-a662-7e99253a6a5d","status":"N","intake":120,"code":"CH","gender":1,"name":"Chemical Engineering","ccode":2601,"yos":1993}},{"node":{"id":"1d6b1266-9d63-5735-ae17-9ec4f46b1542","status":"N","intake":120,"code":"CE","gender":1,"name":"Civil Engineering","ccode":2601,"yos":1993}},{"node":{"id":"29f6bf19-0c68-5413-a9a7-9994e97026a3","status":"N","intake":60,"code":"IT","gender":1,"name":"Information Technology","ccode":2601,"yos":2001}},{"node":{"id":"a5e39623-344b-5358-bb45-641e6846e10c","status":"N","intake":240,"code":"ME","gender":1,"name":"Mechanical Engineering","ccode":2601,"yos":1987}},{"node":{"id":"e130ed84-0ba4-5305-9bcc-9d94d4d9c29b","status":"N","intake":60,"code":"AE","gender":1,"name":"Aeronautical Engineering","ccode":2601,"yos":2009}},{"node":{"id":"c6504035-9c63-5041-988b-673db0eea71e","status":"N","intake":60,"code":"BM","gender":1,"name":"Bio Medical Engineering","ccode":2601,"yos":2003}},{"node":{"id":"d1a145e2-d8b0-555e-9c5d-c9a7d0004568","status":"N","intake":60,"code":"BT","gender":1,"name":"Bio-Technology","ccode":2601,"yos":2003}}],"collegeData":{"id":"8454f798-df07-53e4-9650-e9681c70a699","catcode":4,"gender":1,"collcode":2601,"lat":12.7179,"lng":77.8701,"place":"ChIJwVEfn2R3rjsRH7tHqt7i0Nw","name":"Adhiyamaan College of Engineering(Autonomous)","add1":"Dr. M.G.R. Nagar,Bangalore- District, Hosur Inner Ring Road, Hosur","add2":"Dr. M.G.R. Nagar,Bangalore- District, Hosur Inner Ring Road, Kumudepalli, Hosur, Tamil Nadu 635109, India","locality":"Kumudepalli","slug":"adhiyamaan-college-of-engineering-autonomous-kumudepalli-hosur-krishnagiri-2601","phone_no1":"04344 260 570","www":"http://www.adhiyamaan.ac.in/","autonomous":"Yes","mess_bill_g":"22000","caution_deposit_b":0,"room_rent_boys":"1500","transport_option":"Optional","electricity_charges_g":"150","caution_deposit_g":0,"admission_fee_b":250,"accno1":2147483647,"phone_1":"04344-260570","yos":1987,"mess_type_b":"Veg/Non-Veg","mess_bill_b_myr":2,"room_rent_g_myr":1,"mess_bill_b":"22000","room_rent_g":"1500","elec_charges_g_myr":1,"room_rent_b_myr":1,"transport":"Yes","elec_charges_b_myr":1,"a_boys":"Yes","est_charges_b":"0","per_rental_g":"Permanent","per_rental_b":"Permanent","a_girls":"Yes","electricity_charges_b":"150","fax":"04344-260573","mess_type_g":"Veg/Non-Veg","phone_2":"04344-261001","admission_fee_g":250,"url":"www.adhiyamaan.ac.in","est_charges_g":"0","mobile":"-","mess_bill_g_myr":1,"minority":"No"}}}