{"pageContext":{"branches":[{"node":{"id":"163d43d6-b08e-502d-aa6c-147d41cf45ab","status":"N","intake":60,"code":"CE","gender":1,"name":"Civil Engineering","ccode":3918,"yos":2012}},{"node":{"id":"e892fc3b-1972-5aaa-b17d-ab8cd69c757c","status":"N","intake":60,"code":"CS","gender":1,"name":"Computer Science and Engg.","ccode":3918,"yos":2001}},{"node":{"id":"58d1d90d-138d-556d-81db-2b54c398ec77","status":"N","intake":60,"code":"EE","gender":1,"name":"Electrical and Elec. Engg.","ccode":3918,"yos":2001}},{"node":{"id":"c96a6e63-ab1d-5fd7-ab2a-cab9469de88e","status":"N","intake":60,"code":"ME","gender":1,"name":"Mechanical Engineering","ccode":3918,"yos":2005}},{"node":{"id":"0c8ce7d0-5e6d-58ba-b327-cadf40ebf9fd","status":"N","intake":60,"code":"EC","gender":1,"name":"Electronics and Comm Engg.","ccode":3918,"yos":2001}}],"collegeData":{"id":"2fffd386-4f17-5cfd-84e5-5c4343e3e510","catcode":4,"gender":1,"collcode":3918,"lat":10.2704,"lng":78.7557,"place":"ChIJvYZMnmZ7ADsRVWvyfljXIh8","name":"Shanmuganathan Engineering College","add1":"Pudukkottai - Thirumayam Road, Arasampatti","add2":"Pudukkottai - Thirumayam Rd, Arasampatti, Tamil Nadu 622507, India","locality":"Arasampatti","slug":"shanmuganathan-engineering-college-arasampatti-pudukkottai-3918","phone_no1":"073737 31541","www":"http://www.shanmuganathanengg.in/","autonomous":"No","mess_bill_g":"2400","caution_deposit_b":0,"room_rent_boys":"1000","transport_option":"Optional","electricity_charges_g":"0","caution_deposit_g":0,"admission_fee_b":2500,"accno1":2147483647,"phone_1":"04333-274913","yos":2001,"mess_type_b":"Veg/Non-Veg","mess_bill_b_myr":1,"room_rent_g_myr":1,"mess_bill_b":"2400","room_rent_g":"1000","elec_charges_g_myr":1,"room_rent_b_myr":1,"transport":"Yes","elec_charges_b_myr":1,"a_boys":"Yes","est_charges_b":"0","per_rental_g":"Permanent","per_rental_b":"Permanent","a_girls":"Yes","electricity_charges_b":"0","fax":"04333-274913","mess_type_g":"Veg/Non-Veg","phone_2":"04333-274914","admission_fee_g":2500,"url":"www.shanmuganathanengg.in","est_charges_g":"0","mobile":"9443440692","mess_bill_g_myr":1,"minority":"No"}}}