{"pageContext":{"branches":[{"node":{"id":"223b3c1f-4864-50ff-9999-0a71cac2d9ea","status":"N","intake":60,"code":"IN","gender":1,"name":"Industrial Engineering and Management","ccode":4949,"yos":2010}},{"node":{"id":"3b8e8b7c-9c97-5f8f-8024-7624eeaaa72c","status":"N","intake":60,"code":"ME","gender":1,"name":"Mechanical Engineering","ccode":4949,"yos":2009}},{"node":{"id":"487c3e08-65a8-5a3c-9e98-ae0128cf9c02","status":"N","intake":60,"code":"MU","gender":1,"name":"Mechanical and Automation Engg.","ccode":4949,"yos":2011}},{"node":{"id":"8e9102f2-ee8f-5120-9e46-4c78d56c9afe","status":"N","intake":60,"code":"MC","gender":1,"name":"Mechatronics","ccode":4949,"yos":2012}},{"node":{"id":"a1e3d76a-c6a8-5631-8915-395ce51c9f2d","status":"N","intake":60,"code":"CE","gender":1,"name":"Civil Engineering","ccode":4949,"yos":2009}},{"node":{"id":"8a3c1648-3541-50ca-bec1-8350c4cf3799","status":"N","intake":60,"code":"CS","gender":1,"name":"Computer Science and Engg.","ccode":4949,"yos":2012}},{"node":{"id":"9f9970f2-16b9-564b-88e6-eff15a75d15f","status":"N","intake":60,"code":"EE","gender":1,"name":"Electrical and Elec. Engg.","ccode":4949,"yos":2009}},{"node":{"id":"9f018669-fe0c-5728-96b9-74d9ca5aa160","status":"N","intake":60,"code":"EC","gender":1,"name":"Electronics and Comm Engg.","ccode":4949,"yos":2009}}],"collegeData":{"id":"5b0ecfde-ff0d-53b4-8916-d2badfc4109e","catcode":4,"gender":1,"collcode":4949,"lat":8.6402,"lng":77.6381,"place":"ChIJa_tHYbEUBDsRS9RyHC3HCXk","name":"PSN Institute of Technology and Science","add1":"PSN Nagar, Tirunelveli","add2":"PSN Nagar, PSN College Rd, Tirunelveli, Tamil Nadu 627451, India","locality":"Tirunelveli","slug":"psn-institute-of-technology-and-science-tirunelveli-4949","phone_no1":"04634 279 681","www":null,"autonomous":"No","mess_bill_g":"2200","caution_deposit_b":0,"room_rent_boys":"1000","transport_option":"Optional","electricity_charges_g":"0","caution_deposit_g":0,"admission_fee_b":0,"accno1":2147483647,"phone_1":"04634-279084","yos":2009,"mess_type_b":"Veg/Non-Veg","mess_bill_b_myr":1,"room_rent_g_myr":1,"mess_bill_b":"2300","room_rent_g":"1000","elec_charges_g_myr":1,"room_rent_b_myr":1,"transport":"Yes","elec_charges_b_myr":1,"a_boys":"Yes","est_charges_b":"0","per_rental_g":"Permanent","per_rental_b":"Permanent","a_girls":"Yes","electricity_charges_b":"0","fax":"04634-279086","mess_type_g":"Veg/Non-Veg","phone_2":"04634-279085","admission_fee_g":0,"url":"www.psnits.org","est_charges_g":"0","mobile":"9486507441","mess_bill_g_myr":1,"minority":"No"}}}