{"pageContext":{"branches":[{"node":{"id":"1a96e1aa-3812-55d9-861f-f40031cdf2bc","status":"N","intake":60,"code":"CS","gender":1,"name":"Computer Science and Engg.","ccode":4680,"yos":2013}},{"node":{"id":"6f7e45e5-0a65-52b2-a502-77e9699db19c","status":"N","intake":60,"code":"EE","gender":1,"name":"Electrical and Elec. Engg.","ccode":4680,"yos":2013}},{"node":{"id":"a14bd8ff-4341-5d34-8277-c7795a4fbc7b","status":"N","intake":60,"code":"CE","gender":1,"name":"Civil Engineering","ccode":4680,"yos":2013}},{"node":{"id":"4ae5ddcf-0ba5-5352-a063-ad88e789c368","status":"N","intake":60,"code":"EC","gender":1,"name":"Electronics and Comm Engg.","ccode":4680,"yos":2013}},{"node":{"id":"bd16f774-80cf-5a79-84df-fe823383c5f8","status":"N","intake":60,"code":"ME","gender":1,"name":"Mechanical Engineering","ccode":4680,"yos":2013}}],"collegeData":{"id":"55aef8ed-9041-579a-a8fb-3592397379a4","catcode":4,"gender":1,"collcode":4680,"lat":9.5687,"lng":77.87,"place":"ChIJa9yEe7zTBjsRdqo8DTqLwP4","name":"AAA College of Engineering & Technology","add1":"Kamarajar Educational Road, Amathur, Sivakasi","add2":"Kamarajar Educational Road, Amathur, Sivakasi, Tamil Nadu 626123, India","locality":"Sivakasi","slug":"aaa-college-of-engineering-technology-sivakasi-virudhunagar-4680","phone_no1":"04562 251 111","www":"http://www.aaaenggcoll.ac.in/","autonomous":"No","mess_bill_g":"2100","caution_deposit_b":0,"room_rent_boys":"1500","transport_option":"Optional","electricity_charges_g":"250","caution_deposit_g":0,"admission_fee_b":3000,"accno1":2147483647,"phone_1":"04562-251111","yos":2013,"mess_type_b":"Veg/Non-Veg","mess_bill_b_myr":1,"room_rent_g_myr":1,"mess_bill_b":"2100","room_rent_g":"1500","elec_charges_g_myr":1,"room_rent_b_myr":1,"transport":"Yes","elec_charges_b_myr":1,"a_boys":"Yes","est_charges_b":"0","per_rental_g":"Permanent","per_rental_b":"Permanent","a_girls":"Yes","electricity_charges_b":"250","fax":"04562-228885","mess_type_g":"Veg/Non-Veg","phone_2":"04562-251112","admission_fee_g":3000,"url":"www.aaaenggcoll.ac.in","est_charges_g":"0","mobile":"9443167210","mess_bill_g_myr":1,"minority":"No"}}}