{"pageContext":{"branches":[{"node":{"id":"4f09c227-9251-5e6f-bb2e-554ad8c659aa","status":"N","intake":45,"code":"CS","gender":1,"name":"Computer Science and Engg.","ccode":1439,"yos":2010}},{"node":{"id":"8c332ac9-1639-5686-8669-bcd414ddee1a","status":"N","intake":45,"code":"EE","gender":1,"name":"Electrical and Elec. Engg.","ccode":1439,"yos":2010}},{"node":{"id":"222ddb81-3e44-5d5f-be5c-4b37fb8c893c","status":"N","intake":45,"code":"EC","gender":1,"name":"Electronics and Comm Engg.","ccode":1439,"yos":2010}},{"node":{"id":"d8ae53b3-2c7e-5acd-be0b-f57e230da603","status":"N","intake":90,"code":"ME","gender":1,"name":"Mechanical Engineering","ccode":1439,"yos":2010}}],"collegeData":{"id":"db8d26d2-fbe9-5148-9e14-8ec009d55ae4","catcode":4,"gender":1,"collcode":1439,"lat":12.4977,"lng":79.6361,"place":"ChIJxSgYCBEkUzoRiTkItUWG168","name":"S.R.I Engineering College","add1":"Tiruvannamalai","add2":"SH 115, Tiruvannamalai, Tamil Nadu 604408, India","locality":"Tiruvannamalai","slug":"s-r-i-engineering-college-tiruvannamalai-1439","phone_no1":null,"www":"http://sriinstitutions.com/","autonomous":"No","mess_bill_g":"2000","caution_deposit_b":5000,"room_rent_boys":"1000","transport_option":"Optional","electricity_charges_g":"0","caution_deposit_g":5000,"admission_fee_b":0,"accno1":2147483647,"phone_1":"04183-292881","yos":2010,"mess_type_b":"Veg/Non-Veg","mess_bill_b_myr":1,"room_rent_g_myr":1,"mess_bill_b":"2000","room_rent_g":"1000","elec_charges_g_myr":1,"room_rent_b_myr":1,"transport":"Yes","elec_charges_b_myr":1,"a_boys":"Yes","est_charges_b":"0","per_rental_g":"Permanent","per_rental_b":"Permanent","a_girls":"Yes","electricity_charges_b":"0","fax":"04183-226390","mess_type_g":"Veg/Non-Veg","phone_2":"04183-291569","admission_fee_g":0,"url":"www.sriinstitutions.com","est_charges_g":"0","mobile":"9962362399","mess_bill_g_myr":1,"minority":"No"}}}